LICENSE
MANIFEST.in
README.md
setup.cfg
setup.py
docassemble/__init__.py
docassemble.LAWVWillsClinic.egg-info/PKG-INFO
docassemble.LAWVWillsClinic.egg-info/SOURCES.txt
docassemble.LAWVWillsClinic.egg-info/dependency_links.txt
docassemble.LAWVWillsClinic.egg-info/namespace_packages.txt
docassemble.LAWVWillsClinic.egg-info/not-zip-safe
docassemble.LAWVWillsClinic.egg-info/top_level.txt
docassemble/LAWVWillsClinic/__init__.py
docassemble/LAWVWillsClinic/data/questions/will_clinic.yml
docassemble/LAWVWillsClinic/data/sources/README.md
docassemble/LAWVWillsClinic/data/static/README.md
docassemble/LAWVWillsClinic/data/templates/README.md
docassemble/LAWVWillsClinic/data/templates/last_will_and_testament.docx