Metadata-Version: 2.1
Name: docassemble.LAWVWillsClinic
Version: 1.0.5
Summary: A docassemble extension for creating a basic will during a LAWV Will Clinic
Home-page: https://docassemble.org
Author: System Administrator
Author-email: dhenry@lawv.net
License: The MIT License (MIT)
Platform: UNKNOWN
License-File: LICENSE
